batoms_api/__init__.py
batoms_api/script-api.py
batoms_api/cli/__init__.py
batoms_api/cli/main.py
batoms_api/cli/script-cli.py
batoms_api-0.2.0.dist-info/LICENSE
batoms_api-0.2.0.dist-info/METADATA
batoms_api-0.2.0.dist-info/WHEEL
batoms_api-0.2.0.dist-info/entry_points.txt
batoms_api-0.2.0.dist-info/top_level.txt
batoms_api-0.2.0.dist-info/RECORD
