Metadata-Version: 2.1
Name: batoms-api
Version: 0.2.0
Summary: Drawing and rendering beautiful atoms, molecules using Blender.
Home-page: https://github.com/superstar54/beautiful-atoms-api
Author: Xing Wang
Author-email: xingwang1991@gmail.com
License: GPL
Platform: UNKNOWN
Classifier: License :: OSI Approved :: GNU General Public License v3 (GPLv3)
Classifier: Programming Language :: Python :: 3.7
Requires-Python: >=3.7
License-File: LICENSE
